plotprofile/__init__.py
plotprofile/__main__.py
plotprofile/cli.py
plotprofile/plot.py
plotprofile/styles.json
plotprofile-1.1.1.dist-info/licenses/LICENSE
plotprofile-1.1.1.dist-info/METADATA
plotprofile-1.1.1.dist-info/WHEEL
plotprofile-1.1.1.dist-info/top_level.txt
plotprofile-1.1.1.dist-info/RECORD
