Metadata-Version: 2.4
Name: plotprofile
Version: 1.1.1
Summary: Plot reaction profiles with customizable curves and labels
Author: Dr A Goodfellow
License: MIT
Requires-Python: >=3.8
License-File: LICENSE
Dynamic: license-file
